odoo8_addon_website_event_register_free-8.0.1.1.0-py2.7-nspkg.pth
odoo_addons/website_event_register_free/__openerp__.py
odoo_addons/website_event_register_free/__init__.py
odoo_addons/website_event_register_free/README.rst
odoo_addons/website_event_register_free/view/templates.xml
odoo_addons/website_event_register_free/i18n/nl_NL.po
odoo_addons/website_event_register_free/i18n/ru.po
odoo_addons/website_event_register_free/i18n/it.po
odoo_addons/website_event_register_free/i18n/es.po
odoo_addons/website_event_register_free/i18n/ro.po
odoo_addons/website_event_register_free/i18n/ca.po
odoo_addons/website_event_register_free/i18n/sl.po
odoo_addons/website_event_register_free/i18n/website_event_register_free.pot
odoo_addons/website_event_register_free/i18n/nl.po
odoo_addons/website_event_register_free/i18n/de.po
odoo_addons/website_event_register_free/i18n/fr.po
odoo_addons/website_event_register_free/i18n/pt_BR.po
odoo_addons/website_event_register_free/i18n/el_GR.po
odoo_addons/website_event_register_free/i18n/fi.po
odoo_addons/website_event_register_free/model/event_registration.py
odoo_addons/website_event_register_free/model/__init__.py
odoo_addons/website_event_register_free/controllers/website_event.py
odoo_addons/website_event_register_free/controllers/__init__.py
odoo_addons/website_event_register_free/static/description/icon.png
odoo_addons/website_event_register_free/static/src/css/website_event_register_free.css
odoo8_addon_website_event_register_free-8.0.1.1.0.dist-info/top_level.txt
odoo8_addon_website_event_register_free-8.0.1.1.0.dist-info/WHEEL
odoo8_addon_website_event_register_free-8.0.1.1.0.dist-info/RECORD
odoo8_addon_website_event_register_free-8.0.1.1.0.dist-info/metadata.json
odoo8_addon_website_event_register_free-8.0.1.1.0.dist-info/DESCRIPTION.rst
odoo8_addon_website_event_register_free-8.0.1.1.0.dist-info/METADATA
odoo8_addon_website_event_register_free-8.0.1.1.0.dist-info/namespace_packages.txt
