Metadata-Version: 2.0
Name: odoo8-addon-website-event-register-free
Version: 8.0.1.1.0
Summary: Avoid shopping chart when registering for free events
Home-page: https://www.tecnativa.com
Author: Therp BV,Tecnativa,Antiun Ingeniería S.L.,Odoo Community Association (OCA)
Author-email: support@odoo-community.org
License: AGPL-3
Platform: UNKNOWN
Requires-Dist: odoo (<9.0a,>=8.0a)
Classifier: Programming Language :: Python :: 2.7
Classifier: Framework :: Odoo
Classifier: License :: OSI Approved :: GNU Affero General Public License v3
